{
  "name": "Aganazzar's Scorcher",
  "type": "spell",
  "level": 2,
  "school": "Evocation",
  "casting_time": "action",
  "range_ft": 30,
  "concentration": false,
  "ritual": false,
  "duration_rounds": 0,
  "description": "A line of roaring flame 30 feet long and 5 feet wide emanates from you in a direction you choose. Each creature in the line must make a Dexterity saving throw. A creature takes 3d8 fire damage on a failed save, or half as much damage on a successful one. At Higher Levels: When you cast this spell using a spell slot of 3rd level or higher, the damage increases by 1d8 for each slot level above 2nd.",
  "save_ability": "dex",
  "damage_type": "fire",
  "mechanics": [
    {
      "effect_type": "damage",
      "target": "single_enemy",
      "apply_on": "save_fail",
      "save_ability": "dex",
      "damage": "3d8",
      "damage_type": "fire"
    }
  ]
}
