{
  "name": "Sequester",
  "type": "spell",
  "level": 7,
  "school": "Transmutation",
  "casting_time": "1 action",
  "range_ft": null,
  "concentration": false,
  "ritual": false,
  "duration_rounds": null,
  "description": "By means of this spell, a willing creature or an object can be hidden away, safe from detection for the duration. When you cast the spell and touch the target, it becomes invisible and can\u2019t be targeted by divination spells or perceived through scrying sensors created by divination spells. If the target is a creature, it falls into a state of suspended animation. Time ceases to flow for it, and it doesn\u2019t grow older. You can set a condition for the spell to end early. The condition can be anything you choose, but it must occur or be visible within 1 mile of the target. Examples include \u201cafter 1,000 years\u201d or \u201cwhen the tarrasque awakens.\u201d This spell also ends if the target takes any damage. Shapechange 9th-\u00ad\u2010\u2011level transmutation",
  "save_ability": null,
  "damage_type": null,
  "mechanics": [
    {
      "effect_type": "apply_condition",
      "target": "target",
      "apply_on": "always",
      "condition": "sequester_resolved",
      "duration_rounds": 1,
      "stack_policy": "refresh"
    }
  ]
}
