{
  "name": "Zephyr Strike",
  "type": "spell",
  "level": 1,
  "school": "Transmutation",
  "casting_time": "bonus action",
  "range_ft": 0,
  "concentration": true,
  "ritual": false,
  "duration_rounds": 10,
  "description": "You move like the wind. Until the spell ends, your movement doesn't provoke opportunity attacks. Once before the spell ends, you can give yourself advantage on one weapon attack roll on your turn. That attack deals an extra 1d8 force damage on a hit. Whether you hit or miss, your walking speed increases by 30 feet until the end of that turn.",
  "save_ability": null,
  "damage_type": "force",
  "mechanics": [
    {
      "effect_type": "apply_condition",
      "target": "source",
      "condition": "zephyr_strike_active",
      "duration_rounds": 10,
      "effect_id": "zephyr_strike"
    },
    {
      "effect_type": "next_attack_advantage",
      "target": "source"
    }
  ]
}
