{
  "name": "Aspect of the Wilds",
  "type": "subclass_feature",
  "description": "You gain one of the following options of your choice. Whenever you finish a Long Rest, you can change your choice. Owl: You have Darkvision with a range of 60 feet. If you already have Darkvision, its range increases by 60 feet. Panther: You have a Climb Speed equal to your Speed. Salmon: You have a Swim Speed equal to your Speed.",
  "mechanics": [
    {
      "option": "Owl",
      "grant": "darkvision",
      "range": 60,
      "ifAlreadyHas": "darkvision",
      "rangeIncrease": 60
    },
    {
      "option": "Panther",
      "grant": "climb_speed",
      "value": "equal to your speed"
    },
    {
      "option": "Salmon",
      "grant": "swim_speed",
      "value": "equal to your speed"
    }
  ]
}
