{
  "name": "Bladesinger",
  "description": "Wield Weapon and Wizardry in Elegant Tandem. Bladesingers master a tradition of wizardry that incorporates swordplay and dance. In combat, a Bladesinger uses intricate, elegant maneuvers that fend off harm and allow the Bladesinger to channel magic into devastating attacks and a cunning defense. Many who have observed a Bladesinger at work remember the display as one of the more beautiful experiences in their life—a glorious dance accompanied by a singing blade. Bladesinging is associated with the ancient elven societies that first mastered the art and coined the term. Even today, most Bladesingers still hail from old elven realms, such as Myth Drannor, or from non-elven societies that share land and history with elves, such as the Silver Marches. Wherever they hail from, Bladesingers take their talents all across the Realms to help common people and perform heroic deeds. Most communities greet the arrival of a Bladesinger as a good omen.",
  "mechanics": [
    {
      "grantFeature": "Bladesong"
    },
    {
      "grantFeature": "Training in War and Song"
    }
  ],
  "source_type": "subclass"
}
