{
  "name": "Path of the Totem Warrior",
  "description": "The Path of the Totem Warrior is a spiritual journey, as the barbarian accepts a spirit animal as guide, protector, and inspiration. In battle, your totem spirit fills you with supernatural might, adding magical fuel to your barbarian rage. Most barbarian tribes consider a totem animal to be kin to a particular clan. In such cases, it is unusual for an individual to have more than one totem animal spirit, though exceptions exist.",
  "mechanics": [
    {
      "effect": "subclass_scaffold",
      "meta_type": "subclass_option"
    }
  ],
  "source_type": "subclass"
}
