{
  "name": "Vampire Touched",
  "description": "You increase your Intelligence, Wisdom, or Charisma score by 1, to a maximum of 20. You always have the Spider Climb spell and one 1st-level spell of your choice from the Enchantment or Illusion school prepared. You can cast each of these spells once without expending a spell slot, and you must finish a long rest before you can cast them in this way again. When you cast Spider Climb in this way, you must target yourself. You can also cast these spells using spell slots you have of the appropriate level. Your spellcasting ability for these spells is the ability increased by this feat.",
  "mechanics": [
    {
      "effect_type": "stat_increase",
      "stat": "int",
      "amount": 1,
      "max": 20,
      "choice": [
        "int",
        "wis",
        "cha"
      ]
    },
    {
      "effect_type": "spell_prepared",
      "spell": "Spider Climb",
      "free_cast": "1/long_rest",
      "restriction": "self_only_on_free_cast"
    },
    {
      "effect_type": "spell_prepared",
      "spell_level": 1,
      "school": [
        "Enchantment",
        "Illusion"
      ],
      "free_cast": "1/long_rest"
    },
    {
      "effect_type": "spellcasting_ability",
      "ability_source": "feat_stat_choice"
    }
  ],
  "source_type": "feat"
}
